pyappbundler/__init__.py
pyappbundler/__main__.py
pyappbundler/_version.py
pyappbundler/pyappbundler.py
pyappbundler/templates/iss.tmpl
pyappbundler-0.1.9.dist-info/licenses/LICENSE
pyappbundler-0.1.9.dist-info/METADATA
pyappbundler-0.1.9.dist-info/WHEEL
pyappbundler-0.1.9.dist-info/top_level.txt
pyappbundler-0.1.9.dist-info/RECORD
