Metadata-Version: 2.4
Name: pyappbundler
Version: 0.1.9
Summary: automate bundle a Python application into a single package
Author-email: inerject <kumbalup@gmail.com>
License-Expression: MIT
Project-URL: Homepage, https://github.com/inerject/pyappbundler
Classifier: Programming Language :: Python :: 3
Classifier: Operating System :: OS Independent
Requires-Python: >=3.11
License-File: LICENSE
Requires-Dist: pyinstaller<7.0,>=6.14
Requires-Dist: Jinja2<4.0,>=3.1
Dynamic: license-file
